LICENSE.txt
README.md
setup.py
MSKgeolocation/MSKgeolocation.py
MSKgeolocation/__init__.py
MSKgeolocation.egg-info/PKG-INFO
MSKgeolocation.egg-info/SOURCES.txt
MSKgeolocation.egg-info/dependency_links.txt
MSKgeolocation.egg-info/top_level.txt